rfdocsindexer/__init__.py
rfdocsindexer/cli.py
rfdocsindexer/config.py
rfdocsindexer/indexer.py
rfdocsindexer/models.py
rfdocsindexer/templates/index.html
rfdocsindexer-1.3.0.dist-info/LICENSE
rfdocsindexer-1.3.0.dist-info/METADATA
rfdocsindexer-1.3.0.dist-info/WHEEL
rfdocsindexer-1.3.0.dist-info/entry_points.txt
rfdocsindexer-1.3.0.dist-info/RECORD
