Metadata-Version: 2.1
Name: rfdocsindexer
Version: 1.3.0
Summary: A simple and configurable generator for RobotFramework documentation
Home-page: https://github.com/Vincema/rfdocsindexer
License: Apache-2.0
Keywords: RobotFramework,Documentation,Libdocs,Testing
Author: Vincent Maire
Author-email: maire.vincent31@gmail.com
Requires-Python: >=3.8,<4.0
Classifier: Development Status :: 5 - Production/Stable
Classifier: Framework :: Robot Framework
Classifier: Framework :: Robot Framework :: Tool
Classifier: Intended Audience :: Developers
Classifier: License :: OSI Approved :: Apache Software License
Classifier: Operating System :: Microsoft :: Windows
Classifier: Operating System :: Unix
Classifier: Operating System :: iOS
Classifier: Programming Language :: Python :: 3
Classifier: Programming Language :: Python :: 3.8
Classifier: Programming Language :: Python :: 3.9
Classifier: Programming Language :: Python :: 3.10
Classifier: Programming Language :: Python :: 3.11
Classifier: Programming Language :: Python :: 3.12
Classifier: Topic :: Documentation
Classifier: Topic :: Software Development :: Quality Assurance
Classifier: Topic :: Software Development :: Testing
Requires-Dist: Jinja2 (>=3)
Requires-Dist: click (>=8)
Requires-Dist: pydantic (>=1)
Requires-Dist: robotframework (>=4)
Requires-Dist: toml (>=0)
Project-URL: Repository, https://github.com/Vincema/rfdocsindexer
